{
	"credit": "Made by Benedikt Drexelius",
	"parent": "./cit_item",
	"textures": {
		"0": "item/brown_shulker_box/70005/0",
		"1": "item/brown_shulker_box/70008/0",
		"2": "item/general/wood/26"
	},
	"elements": [
		{
			"from": [-0.00894, 2.45716, -2.66614],
			"to": [15.99106, 8.45716, 13.33386],
			"rotation": {"angle": -22.5, "axis": "x", "origin": [7.99106, 10.45716, 5.33386]},
			"faces": {
				"north": {"uv": [8, 12.5, 16, 16], "texture": "#0"},
				"east": {"uv": [0, 12.5, 8, 16], "texture": "#0"},
				"south": {"uv": [8, 12.5, 16, 16], "texture": "#0"},
				"west": {"uv": [0, 12.5, 8, 16], "texture": "#0"},
				"up": {"uv": [0, 0, 11, 15], "texture": "#1"},
				"down": {"uv": [0, 4, 7.5, 11.5], "texture": "#0"}
			}
		},
		{
			"from": [13.99106, 8.45716, -2.66614],
			"to": [15.99106, 9.45716, 13.33386],
			"rotation": {"angle": -22.5, "axis": "x", "origin": [7.99106, 10.45716, 5.33386]},
			"faces": {
				"north": {"uv": [8, 12, 9, 12.5], "texture": "#0"},
				"east": {"uv": [0, 12, 8, 12.5], "texture": "#0"},
				"south": {"uv": [15, 12, 16, 12.5], "texture": "#0"},
				"west": {"uv": [8, 4, 8.5, 12], "texture": "#0"},
				"up": {"uv": [8, 4, 8.5, 12], "texture": "#0"},
				"down": {"uv": [0, 0, 2, 16], "texture": "#missing"}
			}
		},
		{
			"from": [0.00894, 8.45716, -2.66614],
			"to": [2.00894, 9.45716, 13.33386],
			"rotation": {"angle": -22.5, "axis": "x", "origin": [8.00894, 10.45716, 5.33386]},
			"faces": {
				"north": {"uv": [15, 12, 16, 12.5], "texture": "#0"},
				"east": {"uv": [8, 4, 8.5, 12], "texture": "#0"},
				"south": {"uv": [8, 12, 9, 12.5], "texture": "#0"},
				"west": {"uv": [0, 12, 8, 12.5], "texture": "#0"},
				"up": {"uv": [8, 4, 8.5, 12], "texture": "#0"},
				"down": {"uv": [2, 0, 0, 16], "texture": "#missing"}
			}
		},
		{
			"from": [2.00894, 8.45716, -2.66614],
			"to": [14.00894, 9.45716, -0.66614],
			"rotation": {"angle": -22.5, "axis": "x", "origin": [8.00894, 10.45716, 5.33386]},
			"faces": {
				"north": {"uv": [9, 12, 15, 12.5], "texture": "#0"},
				"east": {"uv": [0, 0, 2, 1], "texture": "#missing"},
				"south": {"uv": [9, 4, 15, 4.5], "texture": "#0"},
				"west": {"uv": [0, 0, 2, 1], "texture": "#missing"},
				"up": {"uv": [9, 4, 15, 4.5], "texture": "#0"},
				"down": {"uv": [2, 0, 14, 2], "texture": "#missing"}
			}
		},
		{
			"from": [2.00894, 8.45716, 11.33386],
			"to": [14.00894, 9.45716, 13.33386],
			"rotation": {"angle": -22.5, "axis": "x", "origin": [8.00894, 10.45716, 5.33386]},
			"faces": {
				"north": {"uv": [9, 4, 15, 4.5], "texture": "#0"},
				"east": {"uv": [0, 0, 2, 1], "texture": "#missing"},
				"south": {"uv": [9, 12, 15, 12.5], "texture": "#0"},
				"west": {"uv": [0, 0, 2, 1], "texture": "#missing"},
				"up": {"uv": [9, 4, 15, 4.5], "texture": "#0"},
				"down": {"uv": [2, 0, 14, 2], "texture": "#missing"}
			}
		},
		{
			"from": [0, 0, 10],
			"to": [16, 4, 14],
			"faces": {
				"north": {"uv": [0, 12, 15, 15], "texture": "#2"},
				"east": {"uv": [12, 12, 15, 15], "texture": "#2"},
				"south": {"uv": [0, 12, 15, 15], "texture": "#2"},
				"west": {"uv": [12, 12, 15, 15], "texture": "#2"},
				"up": {"uv": [0, 12, 15, 15], "texture": "#2"},
				"down": {"uv": [0, 12, 15, 15], "texture": "#2"}
			}
		},
		{
			"from": [7, 1.25, 10.25],
			"to": [11, 16.25, 13.25],
			"rotation": {"angle": 45, "axis": "x", "origin": [9, 12.25, 11.75]},
			"faces": {
				"north": {"uv": [4, 0, 0, 15], "texture": "#1"},
				"east": {"uv": [7, 0, 4, 15], "texture": "#1"},
				"south": {"uv": [10.957, 0, 6.957, 15], "texture": "#1"},
				"west": {"uv": [4, 0, 7, 15], "texture": "#1"},
				"up": {"uv": [11, 3, 15, 0], "texture": "#1"}
			}
		},
		{
			"from": [3, 1.25, 8.25],
			"to": [7, 16.25, 11.25],
			"rotation": {"angle": 45, "axis": "x", "origin": [5, 12.25, 9.75]},
			"faces": {
				"north": {"uv": [4, 0, 0, 15], "texture": "#1"},
				"east": {"uv": [7, 0, 4, 15], "texture": "#1"},
				"south": {"uv": [11, 0, 7, 15], "texture": "#1"},
				"west": {"uv": [4, 0, 7, 15], "texture": "#1"},
				"up": {"uv": [11, 3, 15, 0], "texture": "#1"}
			}
		},
		{
			"from": [9, 1.25, 6.75],
			"to": [13, 16.25, 9.75],
			"rotation": {"angle": 45, "axis": "x", "origin": [11, 12.25, 8.25]},
			"faces": {
				"north": {"uv": [4, 0, 0, 15], "texture": "#1"},
				"east": {"uv": [6.957, 0, 3.957, 15], "texture": "#1"},
				"south": {"uv": [11, 0, 7, 15], "texture": "#1"},
				"west": {"uv": [4, 0, 7, 15], "texture": "#1"},
				"up": {"uv": [11, 3, 15, 0], "texture": "#1"}
			}
		}
	],
	"display": {
		"thirdperson_righthand": {
			"rotation": [75, 45, 0],
			"translation": [0, 2.5, 0],
			"scale": [0.375, 0.375, 0.375]
		},
		"thirdperson_lefthand": {
			"rotation": [75, 45, 0],
			"translation": [0, 2.5, 0],
			"scale": [0.375, 0.375, 0.375]
		},
		"firstperson_righthand": {
			"rotation": [0, 45, 0],
			"translation": [0, 2.25, 0],
			"scale": [0.4, 0.4, 0.4]
		},
		"firstperson_lefthand": {
			"rotation": [0, 225, 0],
			"translation": [0, 3.25, 0],
			"scale": [0.4, 0.4, 0.4]
		},
		"ground": {
			"translation": [0, 0.25, 0],
			"scale": [0.5, 0.5, 0.5]
		},
		"gui": {
			"rotation": [30, 225, 0],
			"translation": [0, 2.5, 0],
			"scale": [0.625, 0.625, 0.625]
		},
		"head": {
			"translation": [0, 14.5, 0]
		},
		"fixed": {
			"rotation": [-90, 0, 0],
			"translation": [0, 0, -15.25],
			"scale": [2, 2, 2]
		}
	},
	"groups": [
		0,
		1,
		2,
		3,
		4,
		5,
		{
			"name": "bread_4",
			"origin": [8, 8, 8],
			"color": 0,
			"children": [6, 7, 8]
		}
	]
}